pitu/__init__.py
pitu/avatar.py
pitu/cli.py
pitu/cover.py
pitu/cut.py
pitu/flip.py
pitu/font.py
pitu/gray.py
pitu/grid.py
pitu/photo.py
pitu/pin.py
pitu/pinstyle.py
pitu/program.py
pitu/rotate.py
pitu/text.py
pitu/utils.py
pitu/zoom.py
pitu-0.3.0.dist-info/LICENSE
pitu-0.3.0.dist-info/METADATA
pitu-0.3.0.dist-info/WHEEL
pitu-0.3.0.dist-info/entry_points.txt
pitu-0.3.0.dist-info/top_level.txt
pitu-0.3.0.dist-info/RECORD
